MANIFEST.in
README.rst
setup.py
sourpy/__init__.py
sourpy/common.py
sourpy/suser.py
sourpy.egg-info/PKG-INFO
sourpy.egg-info/SOURCES.txt
sourpy.egg-info/dependency_links.txt
sourpy.egg-info/not-zip-safe
sourpy.egg-info/requires.txt
sourpy.egg-info/top_level.txt
test/test_debe.py
test/test_entry.py
test/test_gundem.py
test/test_user.py