Metadata-Version: 1.1
Name: sourpy
Version: 0.2.1
Summary: Ekşi Sözlük scraper
Home-page: https://github.com/canpolat/sourpy
Author: Eren Inan Canpolat
Author-email: eren.canpolat@gmail.com
License: UNKNOWN
Platform: UNKNOWN
Classifier: Development Status :: 3 - Alpha
Classifier: Intended Audience :: Developers
Classifier: Environment :: Web Environment
Classifier: License :: OSI Approved :: GNU General Public License v3 or later (GPLv3+)
Classifier: Natural Language :: English
Classifier: Operating System :: OS Independent
Classifier: Programming Language :: Python :: 2.7
Classifier: Topic :: Internet
